complex_decimal_pluit/ComplexDecimal.py
complex_decimal_pluit/__init__.py
complex_decimal_pluit-0.0.1.dist-info/METADATA
complex_decimal_pluit-0.0.1.dist-info/WHEEL
complex_decimal_pluit-0.0.1.dist-info/licenses/LICENSE
complex_decimal_pluit-0.0.1.dist-info/RECORD
