Metadata-Version: 2.1
Name: complex_decimal_pluit
Version: 0.0.1
Summary: Complex numbers with arbitrary precision in python
Project-URL: Homepage, https://github.com/DaniaRepublic/ComplexDecimal
Author-email: imarkin <imdaniarepublic@gmail.com>
License: Copyright (c) 2018 The Python Packaging Authority
License-File: LICENSE
Classifier: License :: OSI Approved :: MIT License
Classifier: Operating System :: OS Independent
Classifier: Programming Language :: Python :: 3
Requires-Python: >=3.7
